{"format":{"bit_rate":"9092898","duration":"248.569208","filename":"tracks/test.flac","format_long_name":"raw FLAC","format_name":"flac","nb_programs":0,"nb_streams":1,"probe_score":100,"size":"282526833","start_time":"0.000000","tags":{"ARTIST":"Prince Fatty","TITLE":"Revolution","album_artist":"120bpm - C","comment":"120bpm - C"}},"streams":[{"avg_frame_rate":"0/0","bits_per_raw_sample":"24","bits_per_sample":0,"channel_layout":"7.1","channels":8,"codec_long_name":"FLAC (Free Lossless Audio Codec)","codec_name":"flac","codec_tag":"0x0000","codec_tag_string":"[0][0][0][0]","codec_type":"audio","disposition":{"attached_pic":0,"captions":0,"clean_effects":0,"comment":0,"default":0,"dependent":0,"descriptions":0,"dub":0,"forced":0,"hearing_impaired":0,"karaoke":0,"lyrics":0,"metadata":0,"original":0,"still_image":0,"timed_thumbnails":0,"visual_impaired":0},"duration":"248.569208","duration_ts":47725288,"extradata_size":34,"index":0,"r_frame_rate":"0/0","sample_fmt":"s32","sample_rate":"192000","start_pts":0,"start_time":"0.000000","time_base":"1/192000"}]}